{"id": 14, "title": "Employ\u00e9", "experience": [{"title": "chef de file mondiale des services collectifs", "description": "Veolia est une multinationale fran\u00e7aise, chef de file mondiale des services collectifs. Veolia propose \u00e0\nses clients, collectivit\u00e9s locales et entreprises, une expertise dans trois domaines compl\u00e9mentaires : \ngestion du cycle de l'eau, gestion et valorisation des d\u00e9chets et gestion de l'\u00e9nergie.\n\nConsultante BI\n\nChallenge(s) / Objectifs de la mission \n* Traitement des incidents\n* D\u00e9veloppement de nouveau projet\n* Suivi et maintenance \u00e9volutive des projets\n\nRessources\n* 2 Consultants BI et 1 R\u00e9f\u00e9rent technique\n\nT\u00e2ches\n* D\u00e9veloppement de rapports de restitution et tableaux de bord ; \n* Maintenance et \u00e9volution de mod\u00e8les Framework ; \n* Analyse des besoins fonctionnels\n* R\u00e9daction des sp\u00e9cifications techniques ; \n* Conception et d\u00e9veloppement des flux d'alimentations ; \n* Audit, correction et monitoring de la qualit\u00e9 des donn\u00e9es ; \n* Tests unitaires et assistance \u00e0 la recette ; \n* Administration du portail : S\u00e9curit\u00e9 et organisation. ; \n* R\u00e9daction des documents d'exploitation\n\nR\u00e9sultats\n* Ma\u00eetrise de la solution IBM Cognos. ; \n* D\u00e9velopper un esprit de raisonnement, d'analyse et de r\u00e9activit\u00e9.\n\nEnvironnement technique :\nIBM Cognos Data Manager, Report Studio, Framework", "duration": 58}]}